halo_fdca/__init__.py
halo_fdca/fdca_logger.py
halo_fdca/fdca_utils.py
halo_fdca/fits_cutout.py
halo_fdca/halo_object.py
halo_fdca/mcmc_fitting_multicomponent.py
halo_fdca/plot_fits.py
halo_fdca/processing.py
halo_fdca/processing_multicomponent.py
halo_fdca-1.0.dist-info/LICENSE
halo_fdca-1.0.dist-info/METADATA
halo_fdca-1.0.dist-info/WHEEL
halo_fdca-1.0.dist-info/top_level.txt
halo_fdca-1.0.dist-info/RECORD
