Metadata-Version: 2.1
Name: halo_fdca
Version: 1.0
Summary: Fit 2D proflile of Radio Halos from FITS files 
Author-email: "J. M. Boxelaar" <j.boxelaar@ira.inaf.it>
Project-URL: Homepage, https://github.com/JortBox/Halo-FDCA
Project-URL: Issues, https://github.com/JortBox/Halo-FDCA/issues
Classifier: Programming Language :: Python :: 3
Classifier: License :: OSI Approved :: GNU General Public License v3 (GPLv3)
Requires-Python: >=3.11
License-File: LICENSE
Requires-Dist: numpy
Requires-Dist: scipy
Requires-Dist: matplotlib
Requires-Dist: astropy>5.0.0
Requires-Dist: pyregion
Requires-Dist: scikit-image
Requires-Dist: emcee
Requires-Dist: corner
Requires-Dist: tqdm
Requires-Dist: pandas
Requires-Dist: astroquery
